dr_sdk_lotr/__init__.py
dr_sdk_lotr/books.py
dr_sdk_lotr/chapters.py
dr_sdk_lotr/characters.py
dr_sdk_lotr/movies.py
dr_sdk_lotr/quotes.py
dr_sdk_lotr/settings.py
dr_sdk_lotr-0.0.5.dist-info/LICENCE.txt
dr_sdk_lotr-0.0.5.dist-info/METADATA
dr_sdk_lotr-0.0.5.dist-info/WHEEL
dr_sdk_lotr-0.0.5.dist-info/top_level.txt
dr_sdk_lotr-0.0.5.dist-info/RECORD
